odoo8_addon_website_container_fluid-8.0.1.0.1.99.dev19-py2.7-nspkg.pth
odoo8_addon_website_container_fluid-8.0.1.0.1.99.dev19.dist-info/DESCRIPTION.rst
odoo8_addon_website_container_fluid-8.0.1.0.1.99.dev19.dist-info/METADATA
odoo8_addon_website_container_fluid-8.0.1.0.1.99.dev19.dist-info/RECORD
odoo8_addon_website_container_fluid-8.0.1.0.1.99.dev19.dist-info/WHEEL
odoo8_addon_website_container_fluid-8.0.1.0.1.99.dev19.dist-info/metadata.json
odoo8_addon_website_container_fluid-8.0.1.0.1.99.dev19.dist-info/namespace_packages.txt
odoo8_addon_website_container_fluid-8.0.1.0.1.99.dev19.dist-info/top_level.txt
odoo_addons/website_container_fluid/README.rst
odoo_addons/website_container_fluid/__init__.py
odoo_addons/website_container_fluid/__openerp__.py
odoo_addons/website_container_fluid/demo/pages.xml
odoo_addons/website_container_fluid/i18n/bg.po
odoo_addons/website_container_fluid/i18n/de.po
odoo_addons/website_container_fluid/i18n/el_GR.po
odoo_addons/website_container_fluid/i18n/es.po
odoo_addons/website_container_fluid/i18n/fr.po
odoo_addons/website_container_fluid/i18n/it.po
odoo_addons/website_container_fluid/i18n/pt_BR.po
odoo_addons/website_container_fluid/i18n/ru.po
odoo_addons/website_container_fluid/i18n/sl.po
odoo_addons/website_container_fluid/i18n/website_container_fluid.pot
odoo_addons/website_container_fluid/static/description/icon.png
odoo_addons/website_container_fluid/static/src/css/styles.css
odoo_addons/website_container_fluid/static/src/css/styles.css.map
odoo_addons/website_container_fluid/static/src/css/styles.sass
odoo_addons/website_container_fluid/views/assets.xml
odoo_addons/website_container_fluid/views/snippets.xml
